databend_udf/__init__.py
databend_udf/client.py
databend_udf/udf.py
databend_udf-0.2.20.dist-info/METADATA
databend_udf-0.2.20.dist-info/WHEEL
databend_udf-0.2.20.dist-info/top_level.txt
databend_udf-0.2.20.dist-info/RECORD
