Metadata-Version: 2.4
Name: databend-udf
Version: 0.2.20
Summary: Databend UDF Server
License: Apache-2.0
Project-URL: Repository, https://github.com/databendlabs/databend-udf
Project-URL: Homepage, https://databend.com
Classifier: Programming Language :: Rust
Classifier: Programming Language :: Python :: Implementation :: CPython
Classifier: Programming Language :: Python :: Implementation :: PyPy
Requires-Python: >=3.7
Requires-Dist: pyarrow
Requires-Dist: prometheus-client>=0.17.0
Provides-Extra: lint
Requires-Dist: ruff; extra == "lint"
Provides-Extra: test
Requires-Dist: pytest; extra == "test"
